random_username/__init__.py
random_username/__main__.py
random_username/generate.py
random_username/data/adjectives.txt
random_username/data/nouns.txt
src/__init__.py
src/__main__.py
src/data/adjectives.txt
src/data/nouns.txt
random_username-1.0.2.dist-info/METADATA
random_username-1.0.2.dist-info/WHEEL
random_username-1.0.2.dist-info/entry_points.txt
random_username-1.0.2.dist-info/top_level.txt
random_username-1.0.2.dist-info/RECORD
