Metadata-Version: 2.1
Name: random-username
Version: 1.0.2
Summary: Randomly generate compelling usernames.
Home-page: https://github.com/williexu/random_username
Author: williexu
Author-email: wx44@cornell.edu
License: MIT
Platform: UNKNOWN
Classifier: License :: OSI Approved :: MIT License
Classifier: Programming Language :: Python
Classifier: Programming Language :: Python :: 2
Classifier: Programming Language :: Python :: 2.7
Classifier: Programming Language :: Python :: 3
Classifier: Programming Language :: Python :: 3.7
